de4rec/__init__.py
de4rec/text_encoder.py
de4rec/train.py
de4rec-0.9.0.dist-info/METADATA
de4rec-0.9.0.dist-info/WHEEL
de4rec-0.9.0.dist-info/top_level.txt
de4rec-0.9.0.dist-info/RECORD
